avocado_price_predictor_model/__init__.py
avocado_price_predictor_model/load_data.py
avocado_price_predictor_model/load_model.py
avocado_price_predictor_model/predict.py
avocado_price_predictor_model/preprocess.py
tests/__init__.py
tests/tests.py
avocado_price_predictor_model-1.0.0.dist-info/LICENSE
avocado_price_predictor_model-1.0.0.dist-info/METADATA
avocado_price_predictor_model-1.0.0.dist-info/WHEEL
avocado_price_predictor_model-1.0.0.dist-info/top_level.txt
avocado_price_predictor_model-1.0.0.dist-info/RECORD
