Metadata-Version: 2.1
Name: avocado-price-predictor-model
Version: 1.0.0
Summary: Avocado Price Prediction Model
Home-page: https://github.com/shaySirek/avocado-price-predictor-model
Author: Shay Sirek
Author-email: shaysirek@gmail.com
License: UNKNOWN
Project-URL: Bug Tracker, https://github.com/shaySirek/avocado-price-predictor-model/issues
Platform: UNKNOWN
Classifier: Programming Language :: Python :: 3
Classifier: License :: OSI Approved :: MIT License
Classifier: Operating System :: OS Independent
Requires-Python: >=3.7
License-File: LICENSE
Requires-Dist: scikit-learn (==0.22.2.post1)
Requires-Dist: pandas
Requires-Dist: gdown
